Metadata-Version: 2.1
Name: sparsify
Version: 1.6.1
Summary: Easy-to-use UI for automatically sparsifying neural networks and creating sparsification recipes for better inference performance and a smaller footprint
Home-page: https://github.com/neuralmagic/sparsify
Author: Neuralmagic, Inc.
Author-email: support@neuralmagic.com
License: Apache
Keywords: inference,machine learning,neural network,computer vision,nlp,cv,deep learning,torch,pytorch,tensorflow,keras,automl,sparsity,pruning,deep learning libraries,onnx,quantization
Platform: UNKNOWN
Classifier: Development Status :: 5 - Production/Stable
Classifier: Programming Language :: Python :: 3
Classifier: Programming Language :: Python :: 3 :: Only
Classifier: Programming Language :: Python :: 3.8
Classifier: Programming Language :: Python :: 3.8
Classifier: Programming Language :: Python :: 3.9
Classifier: Intended Audience :: Developers
Classifier: Intended Audience :: Education
Classifier: Intended Audience :: Information Technology
Classifier: Intended Audience :: Science/Research
Classifier: License :: OSI Approved :: Apache Software License
Classifier: Operating System :: POSIX :: Linux
Classifier: Topic :: Scientific/Engineering
Classifier: Topic :: Scientific/Engineering :: Artificial Intelligence
Classifier: Topic :: Scientific/Engineering :: Mathematics
Classifier: Topic :: Software Development
Classifier: Topic :: Software Development :: Libraries :: Python Modules
Requires-Python: >=3.8.0
License-File: LICENSE
License-File: NOTICE
Requires-Dist: sparsezoo ~=1.6
Requires-Dist: deepsparse ~=1.6
Requires-Dist: sparseml[torchvision,yolov5] ~=1.6
Requires-Dist: pydantic <2.0.0,>=1.8.2
Requires-Dist: pyyaml >=5.0.0
Requires-Dist: click ~=8.0.0
Requires-Dist: tensorboard >=2.0.0
Requires-Dist: setuptools >=56.0.0
Requires-Dist: optuna >=3.0.2
Requires-Dist: onnxruntime-gpu
Provides-Extra: dev
Requires-Dist: black >=20.8b1 ; extra == 'dev'
Requires-Dist: flake8 >=3.8.3 ; extra == 'dev'
Requires-Dist: isort >=5.7.0 ; extra == 'dev'
Requires-Dist: pytest >=6.0.0 ; extra == 'dev'
Requires-Dist: wheel >=0.36.2 ; extra == 'dev'
Requires-Dist: fastai >=2.7.7 ; extra == 'dev'
Provides-Extra: llm
Requires-Dist: llm-foundry ==0.2.0 ; extra == 'llm'
Requires-Dist: nm-transformers ; extra == 'llm'
Provides-Extra: nm
Requires-Dist: sparsezoo ~=1.6 ; extra == 'nm'
Requires-Dist: deepsparse ~=1.6 ; extra == 'nm'
Requires-Dist: sparseml[torchvision,yolov5] ~=1.6 ; extra == 'nm'
